CHANGES.md
LICENSE
MANIFEST.in
README.md
flask_xsrf.py
flask_xsrf_tests.py
requirements.txt
setup.cfg
setup.py
flask_xsrf.egg-info/PKG-INFO
flask_xsrf.egg-info/SOURCES.txt
flask_xsrf.egg-info/dependency_links.txt
flask_xsrf.egg-info/not-zip-safe
flask_xsrf.egg-info/requires.txt
flask_xsrf.egg-info/top_level.txt