Metadata-Version: 1.1
Name: flask-xsrf
Version: 1.0.2
Summary: 
